iambcodes/Create_New_ConfFile.py
iambcodes/__init__.py
iambcodes/analytics.py
iambcodes/biolog.py
iambcodes/bsfun.py
iambcodes/cobra.py
iambcodes/fasta.py
iambcodes/homeworks.py
iambcodes/judas.py
iambcodes/rates.py
iambcodes-0.1.20.dist-info/LICENSE
iambcodes-0.1.20.dist-info/METADATA
iambcodes-0.1.20.dist-info/WHEEL
iambcodes-0.1.20.dist-info/top_level.txt
iambcodes-0.1.20.dist-info/RECORD
