Metadata-Version: 2.1
Name: iambcodes
Version: 0.1.20
Summary: Functions for data analysis support at the iAMB in RWTH Aachen.
Home-page: https://git.rwth-aachen.de/ulf.liebal/iambcodes
Author: Ulf Liebal
Author-email: ulf.liebal@rwth-aachen.de
License: UNKNOWN
Keywords: biotechnology
Platform: UNKNOWN
Requires-Python: >=3.6
License-File: LICENSE
Requires-Dist: xlrd (>=2.0.1)
Requires-Dist: numpy (==1.21)
Requires-Dist: pandas (>=1.3.4)
Requires-Dist: cobra (>=0.22.1)
Requires-Dist: biopython (>=1.78)
Requires-Dist: matplotlib (>=3.3.4)
Requires-Dist: scipy (>=1.9.0)
Requires-Dist: openpyxl (>=3.0.9)
Requires-Dist: xlsxwriter (>=3.0.1)
